<tool id="ROMInfo">
	<img src="../../Resources/Logiqx.gif" width="327" height="68"/>
	<img src="ROMInfo.gif" width="107" height="40"/>

	<name>ROMInfo</name>
	<version>v2.3</version>
	<status></status>
	<date>28/02/2005</date>

	<description>ROM identification tool (for individual ROMs)</description>

	<comment>
		<p>ROMInfo is for identifying arcade ROMs and checking if they are emulated yet.<br /> It does this using the <a href="../../Dats/Dats.php">CMPro dats</a> from the <a href="http://caesar.logiqx.com/">CAESAR</a> database and should cover every arcade game emulated so far.</p>
	</comment>

	<downloads>
		<download>
			<file name="rinfo23.zip" size="123"/>
		</download>
	</downloads>

	<revisions>
		<revision>
			<date>28 February 2005</date>
			<version>v2.3</version>
			<comment>
				- Uses DatLib v2.2. <br />
				- Added support for tab delimited files.<br />
			</comment>
		</revision>

		<revision>
			<date>22 July 2004</date>
			<version>v2.2</version>
			<comment>
				- Uses DatLib v1.8. <br />
				- Removed the need for xml2info by adding my own MAME XML parser. <br />
				- A nice side effect is that names like "Alien<sup>3</sup>: The Gun" work now!<br />
			</comment>
		</revision>

		<revision>
			<date>11 July 2004</date>
			<version>v2.1</version>
			<comment>
				- Updated the source to use the new functions of DatLib v1.4. <br />
				- There is no functional change within ROMInfo though.<br />
			</comment>
		</revision>

		<revision>
			<date>2 July 2004</date>
			<version>v2.0</version>
			<comment>
				- Modified to use DatLib - there are no game or ROM limits anymore! <br />
				- Also supports all DatLib formats (ListInfo, XML, RomCenter, etc). <br />
				- Note: For XML support to work, you need xml2info.exe in your path.<br />
			</comment>
		</revision>

		<revision>
			<date>22 January 2001</date>
			<version>v1.03</version>
			<comment>
				- Added standard file support. <br />
				- Added support for multiple CRCs/files/zips. <br />
				- Added automatic logging (sends output to rominfo.log). <br />
				- Other minor improvements to the output format and the source code.<br />
			</comment>
		</revision>

		<revision>
			<date>6 January 2001</date>
			<version>v1.02</version>
			<comment>
				- Drag and drop support added.<br />
			</comment>
		</revision>

		<revision>
			<date>31 December 2000</date>
			<version>v1.01</version>
			<comment>
				- ZIP support added.<br />
			</comment>
		</revision>

		<revision>
			<date>30 December 2000</date>
			<version>v1.0</version>
			<comment>
				- First public release.<br />
			</comment>
		</revision>
	</revisions>
</tool>
